ntmemoryapi/__init__.py
ntmemoryapi/embed.py
ntmemoryapi/misc.py
ntmemoryapi-1.4.0.dist-info/WHEEL
ntmemoryapi-1.4.0.dist-info/entry_points.txt
ntmemoryapi-1.4.0.dist-info/METADATA
ntmemoryapi-1.4.0.dist-info/RECORD
