Metadata-Version: 2.3
Name: ntmemoryapi
Version: 1.4.0
Summary: Simple library for Windows to manipulate process virtual memory with stelthy syscall wraps
Author: Xenely
Requires-Dist: psutil>=7.1.3
Requires-Python: >=3.10
